MANIFEST.in
README
batman.mp3
batman.wav
daffy_language.mp3
setup.py
bin/batmancomplex
bin/godcomplex
bin/swearcomplex
godcomplex/__init__.py
godcomplex.egg-info/PKG-INFO
godcomplex.egg-info/SOURCES.txt
godcomplex.egg-info/dependency_links.txt
godcomplex.egg-info/not-zip-safe
godcomplex.egg-info/requires.txt
godcomplex.egg-info/top_level.txt