Metadata-Version: 1.0
Name: godcomplex
Version: 0.1.0
Summary: this will say something if you say god. or other stuff
Home-page: UNKNOWN
Author: Isaac Robinson
Author-email: isaacrob@me.com
License: GNU
Keywords: god,irony,speech recognition
Platform: UNKNOWN
